neon_phal_plugin_gui_network_client/__init__.py
neon_phal_plugin_gui_network_client/version.py
neon_phal_plugin_gui_network_client/locale/ca-es/debug_ap_created.dialog
neon_phal_plugin_gui_network_client/locale/ca-es/debug_ap_start.dialog
neon_phal_plugin_gui_network_client/locale/ca-es/debug_ap_stop.dialog
neon_phal_plugin_gui_network_client/locale/ca-es/debug_ap_stopped.dialog
neon_phal_plugin_gui_network_client/locale/ca-es/debug_connecting.dialog
neon_phal_plugin_gui_network_client/locale/ca-es/debug_end_setup.dialog
neon_phal_plugin_gui_network_client/locale/ca-es/debug_http_started.dialog
neon_phal_plugin_gui_network_client/locale/ca-es/debug_start_setup.dialog
neon_phal_plugin_gui_network_client/locale/ca-es/debug_user_connected.dialog
neon_phal_plugin_gui_network_client/locale/ca-es/debug_wifi_connected.dialog
neon_phal_plugin_gui_network_client/locale/ca-es/debug_wifi_error.dialog
neon_phal_plugin_gui_network_client/locale/ca-es/debug_wifi_scanned.dialog
neon_phal_plugin_gui_network_client/locale/ca-es/launch_setup.intent
neon_phal_plugin_gui_network_client/locale/ca-es/wifi_intro.dialog
neon_phal_plugin_gui_network_client/locale/en-us/debug_ap_created.dialog
neon_phal_plugin_gui_network_client/locale/en-us/debug_ap_start.dialog
neon_phal_plugin_gui_network_client/locale/en-us/debug_ap_stop.dialog
neon_phal_plugin_gui_network_client/locale/en-us/debug_ap_stopped.dialog
neon_phal_plugin_gui_network_client/locale/en-us/debug_connecting.dialog
neon_phal_plugin_gui_network_client/locale/en-us/debug_end_setup.dialog
neon_phal_plugin_gui_network_client/locale/en-us/debug_http_started.dialog
neon_phal_plugin_gui_network_client/locale/en-us/debug_start_setup.dialog
neon_phal_plugin_gui_network_client/locale/en-us/debug_user_connected.dialog
neon_phal_plugin_gui_network_client/locale/en-us/debug_wifi_connected.dialog
neon_phal_plugin_gui_network_client/locale/en-us/debug_wifi_error.dialog
neon_phal_plugin_gui_network_client/locale/en-us/debug_wifi_scanned.dialog
neon_phal_plugin_gui_network_client-0.0.6.dist-info/LICENSE
neon_phal_plugin_gui_network_client-0.0.6.dist-info/METADATA
neon_phal_plugin_gui_network_client-0.0.6.dist-info/WHEEL
neon_phal_plugin_gui_network_client-0.0.6.dist-info/entry_points.txt
neon_phal_plugin_gui_network_client-0.0.6.dist-info/top_level.txt
neon_phal_plugin_gui_network_client-0.0.6.dist-info/zip-safe
neon_phal_plugin_gui_network_client-0.0.6.dist-info/RECORD
