Metadata-Version: 2.1
Name: neon-phal-plugin-gui-network-client
Version: 0.0.6
Summary: A PHAL plugin for Neon/OVOS
Home-page: https://github.com/NeonGeckoCom/neon-phal-plugin-gui-network-client
Author: Neongecko
Author-email: defelopers@neon.ai
License: Apache-2.0
Classifier: Development Status :: 3 - Alpha
Classifier: Intended Audience :: Developers
Classifier: Topic :: Text Processing :: Linguistic
Classifier: License :: OSI Approved :: Apache Software License
Classifier: Programming Language :: Python :: 3.5
Classifier: Programming Language :: Python :: 3.6
License-File: LICENSE
Requires-Dist: ovos-plugin-manager~=0.0
Requires-Dist: ovos-bus-client>=0.0.8,~=0.0
Requires-Dist: ovos-utils>=0.0.38,~=0.0
